Metadata-Version: 1.0
Name: BiblioCLI
Version: 0.2.4
Summary: A command line interface for capturing and storing information about books you want to read
Home-page: https://github.com/KeaganStokoe/biblioCLI
Author: Keagan Stokoe
Author-email: keagan.stokoe@gmail.com
License: UNKNOWN
Platform: UNKNOWN
